frigidum/__init__.py
frigidum/annealing.py
frigidum/examples/__init__.py
frigidum/examples/dsjc1000_9.py
frigidum/examples/gcp.py
frigidum/examples/knapsack.py
frigidum/examples/ks_10000_0.py
frigidum/examples/pcb442.py
frigidum/examples/rastrigin.py
frigidum/examples/tsp.py
frigidum-0.4.0.dist-info/METADATA
frigidum-0.4.0.dist-info/WHEEL
frigidum-0.4.0.dist-info/top_level.txt
frigidum-0.4.0.dist-info/RECORD
