Metadata-Version: 2.1
Name: frigidum
Version: 0.4.0
Summary: Simulated Annealing using tqdm
Home-page: https://gitlab.com/whendrik/frigidum
Author: Willem Hendriks
Author-email: whendrik@gmail.com
License: UNKNOWN
Platform: UNKNOWN
Classifier: Programming Language :: Python :: 3
Classifier: License :: OSI Approved :: MIT License
Classifier: Operating System :: OS Independent
Requires-Python: >=3.6
Requires-Dist: tqdm (>=3.4.0)
